dev/util/sync/src/fifo.sv


module fifo
  #(
    parameter int data_size = 0,
    parameter int buffer_size = 0
  ) 
  (
    input logic clk,
    input logic rst_n,

    input  logic [data_size-1:0] enq_data,
    input  logic                 enq_valid,
    output logic                 enq_ready,

    output logic [data_size-1:0] deq_data,
    output logic                 deq_valid,
    input  logic                 deq_ready,

    input logic                 flush,
    output logic                full,
    output logic                empty
  );

if (buffer_size == 1) begin : single_buffer

  logic [data_size-1:0] data;
  logic                 full;
    
  always_ff @(posedge clk or negedge rst_n) begin
    if(~rst_n) begin
      data  <= '0;
      full  <= 1'b0;
    end else begin
      if(flush) begin
        data  <= '0;
        full  <= 1'b0;
      end else begin
        unique case ({enq_valid, deq_ready, full})
          3'b000,
          3'b001,
          3'b010,
          3'b101 : begin
            // Nothing
          end
          3'b011 : begin
            full <= 1'b0;
          end
          3'b100,
          3'b110,
          3'b111 : begin
            data <= enq;
            full <= 1'b1;
          end
        endcase
      end
    end
  end

  assign enq_ready = !full | (full & deq_ready);
  assign deq_valid = full;
  assign deq       = data;

end else if (buffer_size > 1) begin : nsize_buffer

  logic [data_size-1:0] data[buffer_size];
  logic [buffer_size-1:0] wr_ptr;
  logic [buffer_size-1:0] rd_ptr;

  always_ff @(posedge clk) begin
    if(enq_valid && !full) begin
      for(int i = 0; i < buffer_size; i++) begin
        if(wr_ptr[i]) begin
          data[i] <= enq_data;
        end
      end
    end
  end

  always_ff @(posedge clk or negedge rst_n) begin
    if(!rst_n) begin
      wr_ptr <= 1;
      rd_ptr <= 1;
    end if(!flush) begin 
      if(enq_valid && !full) begin
        wr_ptr <= (wr_ptr << 1 == '0) ? (buffer_size)'(1) : wr_ptr << 1;
      end

      if(deq_ready && !empty) begin
        rd_ptr <= (rd_ptr << 1 == '0) ? (buffer_size)'(1) : rd_ptr << 1;
      end
    end if(flush) begin
      rd_ptr <= 1;
      wr_ptr <= 1;
    end
  end

  always_comb begin
    deq_data = '0;
    for(int i = 0; i < buffer_size; i++) begin
      if(rd_ptr[i]) begin
        deq_data = data[i];
      end
    end
    
    enq_ready = !full;
    deq_valid = !empty;
  end

  always_comb begin
    full = (wr_ptr << 1 == 0)? ('1 == rd_ptr) : (wr_ptr << 1 == rd_ptr);
    empty = (wr_ptr == rd_ptr);
  end

end else begin : error
  initial begin
    assert (1) else $fatal("The buffer size shall be greather or equal than 1");
  end
end

endmodule

IPs/UTIL/FIFO/SYNC/tb_fifo.sv


module tb_fifo 
(
  input logic clk,
  input logic rst_n
);

  logic [9:0] enq_data0;
  logic       enq_valid0;
  logic       enq_ready0;
  logic [9:0] deq_data0;
  logic       deq_valid0;
  logic       deq_ready0;
  logic       flush0;
  logic       full0;
  logic       empty0;

  //logic       enq_data1;
  //logic       enq_valid1;
  //logic       enq_ready1;
  //logic       deq_data1;
  //logic       deq_valid1;
  //logic       deq_ready1;
  //logic       flush1;
  //logic       full1;
  //logic       empty1;

  logic [9:0]   value, value_n;

  fifo #(.data_size(10), .buffer_size(5)) fifo_0_i
  (
    .clk       (clk),
    .rst_n     (rst_n),
    .enq_data  (enq_data0),
    .enq_valid (enq_valid0),
    .enq_ready (enq_ready0),
    .deq_data  (deq_data0),
    .deq_valid (deq_valid0),
    .deq_ready (deq_ready0),
    .flush     (flush0),
    .full      (full0),
    .empty     (empty0)
  );

  //fifo #(.data_size(1), .buffer_size(5)) fifo_1_i
  //(
  //  .clk       (clk),
  //  .rst_n     (rst_n),
  //  .enq_data  (enq_data1),
  //  .enq_valid (enq_valid1),
  //  .enq_ready (enq_ready1),
  //  .deq_data  (deq_data1),
  //  .deq_valid (deq_valid1),
  //  .deq_ready (deq_ready1),
  //  .flush     (flush1),
  //  .full      (full1),
  //  .empty     (empty1)
  //);

  typedef enum bit[4:0] {
    IDLE  = 5'h0,
    TEST0 = 5'h1,
    RESP0 = 5'h2,
    TEST1 = 5'h3,
    RESP1 = 5'h4,
    RESP2 = 5'h5,
    GOOD  = 5'h13,
    ERROR = 5'h14
  } FTEST_t;

  FTEST_t f0state, f0state_n;
  //FTEST_t f1state, f1state_n;

  always_ff @(posedge clk or negedge rst_n) begin
    if(!rst_n) begin
      f0state <= IDLE;
      value <= 0;
      //f1state <= IDLE;
    end else begin
      f0state <= f0state_n;
      value <= value_n;
      //f1state <= f1state_n;
    end
  end

  always_comb begin
    f0state_n = f0state;
    enq_data0 = 0;
    enq_valid0 = 0;
    deq_ready0 = 0;
    flush0 = 0;
    value_n = value;

    casez (f0state)
      IDLE : begin
        value_n = 1;
        f0state_n = TEST0;
      end
      TEST0 : begin
        enq_data0 = 10'b1;
        enq_valid0 = 1;
        f0state_n = RESP0;
      end
      RESP0 : begin
        deq_ready0 = 1;
        if(deq_data0 == 10'b1 &&
           deq_valid0 == 1'b1 &&
           enq_ready0 == 1'b1 &&
           full0 == 1'b0 &&
           empty0 == 1'b0) begin
          f0state_n = TEST1;  
        end else begin
          f0state_n = ERROR;
        end
      end
      TEST1 : begin
        enq_data0 = value;
        value_n = value + 1;
        enq_valid0 = 1;
        deq_ready0 = 0;

        if(value == 4) begin
          value_n = 1;
          f0state_n = RESP1;
        end else
          f0state_n = TEST1;
      end
      RESP1 : begin
        deq_ready0 = 1;
        if(deq_data0 == value &&
           deq_valid0 == 1'b1 &&
           enq_ready0 == 1'b0 &&
           full0 == 1'b1 &&
           empty0 == 1'b0) begin
          value_n = 2;
          f0state_n = RESP2;  
        end else begin
          f0state_n = ERROR;
        end
      end
      RESP2 : begin
        deq_ready0 = 1;
        if(deq_data0 == value &&
           deq_valid0 == 1'b1 &&
           enq_ready0 == 1'b1 &&
           full0 == 1'b0 &&
           empty0 == 1'b0) begin
          value_n = value + 1;
          if(value != 4)
            f0state_n = RESP2;  
          else
            f0state_n = GOOD;  
        end else begin
          f0state_n = ERROR;
        end
      end
      GOOD : begin
        $display("GOOD\n");  
        $finish(1);
        $stop(1);
      end
      ERROR : begin
        $display("ERROR\n");  
        $finish(1);
        $stop(1);
      end
      default: begin
        assert (1) else $fatal("Error state");
        $finish(1);
        $stop(1);
      end
    endcase

  end
  
endmodule

IPs/UTIL/waveform.vcd
$version Generated by VerilatedVcd $end
$timescale 1ps $end
 $scope module TOP $end
  $var wire 1 7 clk $end
  $var wire 1 8 rst_n $end
  $scope module tb_fifo $end
   $var wire 1 7 clk $end
   $var wire 1 8 rst_n $end
   $var wire 10 , enq_data0 [9:0] $end
   $var wire 1 - enq_valid0 $end
   $var wire 1 . enq_ready0 $end
   $var wire 10 / deq_data0 [9:0] $end
   $var wire 1 0 deq_valid0 $end
   $var wire 1 1 deq_ready0 $end
   $var wire 1 9 flush0 $end
   $var wire 1 2 full0 $end
   $var wire 1 3 empty0 $end
   $var wire 10 # value [9:0] $end
   $var wire 10 4 value_n [9:0] $end
   $var wire 5 $ f0state [4:0] $end
   $var wire 5 5 f0state_n [4:0] $end
   $scope module fifo_0_i $end
    $var wire 32 : data_size [31:0] $end
    $var wire 32 ; buffer_size [31:0] $end
    $var wire 1 7 clk $end
    $var wire 1 8 rst_n $end
    $var wire 10 , enq_data [9:0] $end
    $var wire 1 - enq_valid $end
    $var wire 1 . enq_ready $end
    $var wire 10 / deq_data [9:0] $end
    $var wire 1 0 deq_valid $end
    $var wire 1 1 deq_ready $end
    $var wire 1 9 flush $end
    $var wire 1 2 full $end
    $var wire 1 3 empty $end
    $scope module nsize_buffer $end
     $var wire 10 & data[0] [9:0] $end
     $var wire 10 ' data[1] [9:0] $end
     $var wire 10 ( data[2] [9:0] $end
     $var wire 10 ) data[3] [9:0] $end
     $var wire 10 * data[4] [9:0] $end
     $var wire 5 6 wr_ptr [4:0] $end
     $var wire 5 % rd_ptr [4:0] $end
     $scope module unnamedblk1 $end
      $var wire 32 + i [31:0] $end
     $upscope $end
     $scope module unnamedblk2 $end
      $var wire 32 < i [31:0] $end
     $upscope $end
    $upscope $end
   $upscope $end
  $upscope $end
 $upscope $end
$enddefinitions $end


#0
b0000000000 #
b00000 $
b00000 %
b0000000000 &
b0000000000 '
b0000000000 (
b0000000000 )
b0000000000 *
b00000000000000000000000000000000 +
b0000000000 ,
0-
1.
b0000000000 /
00
01
02
13
b0000000001 4
b00001 5
b00000 6
17
08
09
b00000000000000000000000000001010 :
b00000000000000000000000000000101 ;
b00000000000000000000000000000101 <
#1
07
#2
b00001 %
b00001 6
17
#3
07
#4
17
#5
07
#6
17
#7
07
#8
17
#9
07
#10
17
#11
07
#12
17
#13
07
#14
17
#15
07
#16
17
#17
07
#18
17
#19
07
#20
17
#21
07
#22
17
#23
07
#24
17
#25
07
#26
17
#27
07
#28
17
#29
07
#30
17
#31
07
#32
17
#33
07
#34
17
#35
07
#36
17
#37
07
#38
17
#39
07
#40
17
#41
07
#42
17
#43
07
#44
17
#45
07
#46
17
#47
07
#48
17
#49
07
#50
17
#51
07
#52
17
#53
07
#54
17
#55
07
#56
17
#57
07
#58
17
#59
07
#60
17
#61
07
#62
17
#63
07
#64
17
#65
07
#66
17
#67
07
#68
17
#69
07
#70
17
#71
07
#72
17
#73
07
#74
17
#75
07
#76
17
#77
07
#78
17
#79
07
#80
17
#81
07
#82
17
#83
07
#84
17
#85
07
#86
17
#87
07
#88
17
#89
07
#90
17
#91
07
#92
17
#93
07
#94
17
#95
07
#96
17
#97
07
#98
17
#99
07
#100
b0000000001 #
b00001 $
b0000000001 ,
1-
b00010 5
17
18
#101
07
#102
b00010 $
b0000000001 &
b00000000000000000000000000000101 +
b0000000000 ,
0-
b0000000001 /
10
11
03
b00011 5
b00010 6
17
#103
07
#104
b00011 $
b00010 %
b0000000001 ,
1-
b0000000000 /
00
01
13
b0000000010 4
17
#105
07
#106
b0000000010 #
b0000000001 '
b0000000010 ,
b0000000001 /
10
03
b0000000011 4
b00100 6
17
#107
07
#108
b0000000011 #
b0000000010 (
b0000000011 ,
b0000000100 4
b01000 6
17
#109
07
#110
b0000000100 #
b0000000011 )
b0000000100 ,
b0000000001 4
b00100 5
b10000 6
17
#111
07
#112
b0000000001 #
b00100 $
b0000000100 *
b0000000000 ,
0-
0.
11
12
b0000000010 4
b00101 5
b00001 6
17
#113
07
#114
b0000000010 #
b00101 $
b00100 %
1.
b0000000010 /
02
b0000000011 4
17
#115
07
#116
b0000000011 #
b01000 %
b0000000011 /
b0000000100 4
17
#117
07
#118
b0000000100 #
b10000 %
b0000000100 /
b0000000101 4
b10011 5
17
